{
    "name": "upload",
    "container-image": {
        "image": "delimz/s_upload",
        "type": "singularity"
    },
    "schema-version": "cytomine-0.1",
    "description": "optional description",
    "command-line": "CYTOMINE_HOST CYTOMINE_PUBLIC_KEY CYTOMINE_PRIVATE_KEY CYTOMINE_ID_PROJECT CYTOMINE_ID_SOFTWARE FILENAME URL ",
    "inputs": [
	    {
	      "id": "cytomine_host",
	      "value-key": "@ID",
	      "command-line-flag": "--@id",
	      "name": "Cytomine host",
	      "description": "Mandatory to communicate with Cytomine; automatically filled by server",
	      "set-by-server": true,
	      "optional": false,
	      "type": "String"
	    },
	    {
	      "id": "cytomine_public_key",
	      "value-key": "@ID",
	      "command-line-flag": "--@id",
	      "name": "Cytomine public key",
	      "description": "Mandatory to communicate with Cytomine; automatically filled by server",
	      "set-by-server": true,
	      "optional": false,
	      "type": "String"
	    },
	    {
	      "id": "cytomine_private_key",
	      "value-key": "@ID",
	      "command-line-flag": "--@id",
	      "name": "Cytomine public key",
	      "description": "Mandatory to communicate with Cytomine; automatically filled by server",
	      "set-by-server": true,
	      "optional": false,
	      "type": "String"
	    },
	    {
	      "id": "cytomine_id_project",
	      "value-key": "@ID",
	      "command-line-flag": "--@id",
	      "name": "Cytomine project ID",
	      "description": "Mandatory to communicate with Cytomine; automatically filled by server",
	      "set-by-server": true,
	      "optional": false,
	      "type": "Number"
	    },
	    {
	      "id": "cytomine_id_software",
	      "value-key": "@ID",
	      "command-line-flag": "--@id",
	      "name": "Cytomine software ID",
	      "description": "Mandatory to communicate with Cytomine; automatically filled by server",
	      "set-by-server": true,
	      "optional": false,
	      "type": "Number"
	    },
	    {
	      "id": "cytomine_log_level",
	      "value-key": "@ID",
	      "command-line-flag": "--@id",
	      "name": "Log verbosity level",
	      "description": "Verbosity level among ['DEBUG', 'INFO', 'WARNING', 'ERROR', 'CRITICAL']",
	      "value-choices": ["DEBUG", "INFO", "WARNING", "ERROR", "CRITICAL"],
	      "optional": true,
	      "type": "String"
	    },
	    {
	      "id": "filename",
	      "value-key": "@ID",
	      "command-line-flag": "--@id",
	      "name": "file name",
	      "description": "optional renaming the downloaded file ",
	      "optional": true,
	      "default-value": null,
	      "type": "String"
	    },
	    {
		    "id": "url",
		    "value-key": "@ID",
		    "command-line-flag": "--@id",
		    "name": "url",
		    "description": "url of the file to upload",
		    "optional" : false,
		    "type": "String"
	    }

    ]
}
